{
  "Document": {
    "DocumentId": 2076072330,
    "Title": "C# Code: “Object.GetHashCode Method (System)”; MSDN",
    "DocumentShortName": null,
    "FileName": null,
    "Path": null,
    "CreateDate": "2010-02-23T16:31:08",
    "ModificationDate": "2010-02-23T16:31:08",
    "TemplateId": null,
    "SegmentId": 83,
    "IsRoot": false,
    "IsActive": true,
    "SortOrdinal": null,
    "ClientId": null,
    "Tag": null
  },
  "Content": "The default implementation of the GetHashCode method does not guarantee unique return values for different objects. Furthermore, the .NET Framework does not guarantee the default implementation of the GetHashCode method, and the value it returns will be the same between different versions of the .NET Framework. Consequently, the default implementation of this method must not be used as a unique object identifier for hashing purposes.\n\n[http://msdn.microsoft.com/en-us/library/system.object.gethashcode.aspx]",
  "Tag": "kb2076072330"
}