{
  "Document": {
    "DocumentId": 936755788,
    "Title": "Bambara Sculpture",
    "DocumentShortName": null,
    "FileName": null,
    "Path": null,
    "CreateDate": "1999-09-07T19:13:58",
    "ModificationDate": "1999-09-07T19:13:58",
    "TemplateId": null,
    "SegmentId": 80,
    "IsRoot": false,
    "IsActive": true,
    "SortOrdinal": null,
    "ClientId": null,
    "Tag": null
  },
  "Content": "Playing With Time : Art and Performance in Central Mali (Traditional Arts of Africa) \nby Mary Jo Arnoldi\nISBN: 025330900X \n\nAfrican Sculpture Speaks \nby Ladislas Segy \nISBN: 0306800187 \n\nVogel, Susan and N'Diaye, Francine - African Masterpieces from the Musee de L'Homme - 1985 - published by Center for African Art (LAPL: 730.996 V879)\n\nVansina, Jan - Art History in Africa - 1984 - publisher: Longman Group (LAPL:709.6 V279)\n\nImperato, Pascal - Mali: A Search for Direction - this book was very helpful in providing info on political history and cultural info.\n\nArnoldi, Mary Jo - Playing with Time - this book included extensive information about the Chi Wara dance.\n\nBambara Sculpture of  West Sudan - 1960 - Museum of Primitive Art/NY - University Publishers\n\nGillon, Werner - Collecting African Art - 1979 - Rizzoli Publishers - includes intro by William Fagg (LAPL: 709.6 G483)\n\nElisoff, Eliot - Sculpture of Africa - 1958 - text by William Fagg - pub. Thames & Hudson\n\nSieber, Roy and Rubin, Arnold - 1968 - Sculpture of Black Africa - pub. by L.A. County Musuem of Art (LAPL: 730.996 S571)\n\nMeauze, Pierre - African Art Sculpture - 1968 - pub. by World Publishing Co. - this man was curator of Arts Africains et Oceaniens in Paris\n\nSegy, Ladislas - African Sculpture Speaks - 3rd Edition - 1969 - pub. by Hill & Wang NY (LAPL: 730.996 S456b)",
  "Tag": "kb936755788"
}